odoo/addons/project_forecast_line_bokeh_chart/README.rst
odoo/addons/project_forecast_line_bokeh_chart/__init__.py
odoo/addons/project_forecast_line_bokeh_chart/__manifest__.py
odoo/addons/project_forecast_line_bokeh_chart/i18n/es.po
odoo/addons/project_forecast_line_bokeh_chart/i18n/fr.po
odoo/addons/project_forecast_line_bokeh_chart/i18n/it.po
odoo/addons/project_forecast_line_bokeh_chart/i18n/project_forecast_line_bokeh_chart.pot
odoo/addons/project_forecast_line_bokeh_chart/readme/CONTRIBUTORS.rst
odoo/addons/project_forecast_line_bokeh_chart/readme/DESCRIPTION.rst
odoo/addons/project_forecast_line_bokeh_chart/report/__init__.py
odoo/addons/project_forecast_line_bokeh_chart/report/forecast_line_reporting.py
odoo/addons/project_forecast_line_bokeh_chart/report/forecast_line_reporting_views.xml
odoo/addons/project_forecast_line_bokeh_chart/security/ir.model.access.csv
odoo/addons/project_forecast_line_bokeh_chart/static/description/icon.png
odoo/addons/project_forecast_line_bokeh_chart/static/description/index.html
odoo_addon_project_forecast_line_bokeh_chart-15.0.1.0.3.1.dist-info/METADATA
odoo_addon_project_forecast_line_bokeh_chart-15.0.1.0.3.1.dist-info/WHEEL
odoo_addon_project_forecast_line_bokeh_chart-15.0.1.0.3.1.dist-info/top_level.txt
odoo_addon_project_forecast_line_bokeh_chart-15.0.1.0.3.1.dist-info/RECORD
